batchdownload/__init__.py
batchdownload/crawler.py
batchdownload-0.1.2.dist-info/licenses/LICENSE
batchdownload-0.1.2.dist-info/METADATA
batchdownload-0.1.2.dist-info/WHEEL
batchdownload-0.1.2.dist-info/entry_points.txt
batchdownload-0.1.2.dist-info/top_level.txt
batchdownload-0.1.2.dist-info/RECORD
