Metadata-Version: 2.4
Name: batchdownload
Version: 0.1.2
Summary: Asynchronous batch directory crawler & downloader
Author-email: Pikachu Ren <pikachuim@foxmail.com>
License: MIT
Project-URL: Homepage, https://github.com/yourname/batchdownload
Project-URL: Repository, https://github.com/yourname/batchdownload
Project-URL: Issues, https://github.com/yourname/batchdownload/issues
Keywords: async,download,crawler,scraper
Classifier: Programming Language :: Python :: 3
Classifier: License :: OSI Approved :: MIT License
Classifier: Operating System :: OS Independent
Requires-Python: >=3.8
License-File: LICENSE
Requires-Dist: aiohttp>=3.8.0
Requires-Dist: aiofiles>=22.0.0
Requires-Dist: playwright>=1.30.0
Requires-Dist: tqdm>=4.64.0
Dynamic: license-file
